llama_index/readers/imap/__init__.py
llama_index/readers/imap/base.py
llama_index_readers_imap-0.2.3.dist-info/METADATA
llama_index_readers_imap-0.2.3.dist-info/WHEEL
llama_index_readers_imap-0.2.3.dist-info/licenses/LICENSE
llama_index_readers_imap-0.2.3.dist-info/RECORD
