Metadata-Version: 2.4
Name: llama-index-readers-imap
Version: 0.2.3
Summary: llama-index readers imap integration
Author-email: Andrea Castellini <and1@live.it>
Maintainer: andyts93
License-Expression: MIT
License-File: LICENSE
Requires-Python: <4.0,>=3.9
Requires-Dist: imap-tools
Requires-Dist: llama-index-core<0.15,>=0.13.0
